CHANGES
COPYING.LGPLv3
LICENSE
MANIFEST.in
README
ez_setup.py
requirements.txt
setup.py
django_staging.egg-info/PKG-INFO
django_staging.egg-info/SOURCES.txt
django_staging.egg-info/dependency_links.txt
django_staging.egg-info/top_level.txt
staging/__init__.py
staging/admin.py
staging/exceptions.py
staging/hg_utils.py
staging/middleware.py
staging/models.py
staging/settings.py
staging/urls.py
staging/utils.py
staging/validators.py
staging/views.py
staging/backends/__init__.py
staging/backends/base.py
staging/backends/content.py
staging/backends/static.py
staging/backends/templates.py