Metadata-Version: 1.0
Name: django-staging
Version: 0.1.0-alpha
Summary: Django staging solution, for maintaining differents servers synchronized. Uses mercurial as backend
Home-page: UNKNOWN
Author: Emilio Sanchez
Author-email: esanchez@yaco.es
License: UNKNOWN
Platform: UNKNOWN
Classifier: Framework :: Django
Classifier: Intended Audience :: Developers
Classifier: License :: OSI Approved :: GNU Library or Lesser General Public License (LGPL)
Classifier: Operating System :: OS Independent
Classifier: Topic :: Internet :: WWW/HTTP
Classifier: Topic :: Internet :: WWW/HTTP :: WSGI
Classifier: Topic :: Internet :: WWW/HTTP :: Dynamic Content
Classifier: Topic :: Software Development :: Libraries :: Application Frameworks
Classifier: Topic :: Software Development :: Libraries :: Python Modules
Classifier: Environment :: Web Environment
Classifier: Programming Language :: Python
